{
    "Arambai": {
        "image_name": "Arambaiicon-DE.png",
        "strong_vs": [
            "Infantry",
            "Villager",
            "Monk",
            "Unit in dense formation"
        ],
        "weak_vs": [
            "Archers (especially skirmishers)",
            "Kamayuk",
            "Huskarl",
            "Mameluke"
        ],
        "wiki_link": "https://ageofempires.fandom.com/wiki/Arambai"
    },
    "Arbalester": {
        "image_name": "Arbalester aoe2DE.png",
        "strong_vs": [
            "Infantry",
            "Villager",
            "Camel unit"
        ],
        "weak_vs": [
            "Skirmisher",
            "Siege unit",
            "Huskarl"
        ],
        "wiki_link": "https://ageofempires.fandom.com/wiki/Arbalester"
    },
    "Archer": {
        "image_name": "Archer aoe2DE.png",
        "strong_vs": [
            "Infantry",
            "Villager"
        ],
        "weak_vs": [
            "Skirmisher",
            "Scout cavalry"
        ],
        "wiki_link": "https://ageofempires.fandom.com/wiki/Archer_(Age_of_Empires_II)"
    },
    "Armored Elephant": {
        "image_name": "AoE2DE Armored Elephant icon.png",
        "strong_vs": [
            "Building",
            "Archer",
            "Trebuchet"
        ],
        "weak_vs": [
            "Infantry",
            "Flaming camel",
            "Cavalry"
        ],
        "wiki_link": "https://ageofempires.fandom.com/wiki/Armored_Elephant_(Age_of_Empires_II)"
    },
    "Ballista Elephant": {
        "image_name": "Ballistaelephanticon-DE.png",
        "strong_vs": [
            "Archer",
            "Massed unit",
            "Especially infantry",
            "Building"
        ],
        "weak_vs": [
            "Eagle warrior",
            "Siege weapon",
            "Monk",
            "Kamayuk"
        ],
        "wiki_link": "https://ageofempires.fandom.com/wiki/Ballista_Elephant"
    },
    "Battering Ram": {
        "image_name": "Battering ram aoe2DE.png",
        "strong_vs": [
            "Building",
            "Archer",
            "Gunpowder unit",
            "Trebuchet"
        ],
        "weak_vs": [
            "Mangudai",
            "Mangonel",
            "Melee units especially magyar huszar",
            "Villager"
        ],
        "wiki_link": "https://ageofempires.fandom.com/wiki/Battering_Ram_(Age_of_Empires_II)"
    },
    "Battle Elephant": {
        "image_name": "Battle elephant aoe2DE.png",
        "strong_vs": [
            "Most melee unit",
            "Building",
            "Resistant to most foot archers"
        ],
        "weak_vs": [
            "Pikeman",
            "Kamayuk",
            "Genoese crossbowman"
        ],
        "wiki_link": "https://ageofempires.fandom.com/wiki/Battle_Elephant"
    },
    "Berserk": {
        "image_name": "BerserkIcon-DE.png",
        "strong_vs": [
            "Skirmisher",
            "Infantry",
            "Cavalry",
            "Eagle warrior",
            "Building"
        ],
        "weak_vs": [
            "Archer unit",
            "Cataphract",
            "Jaguar warrior",
            "Boyar",
            "Samurai"
        ],
        "wiki_link": "https://ageofempires.fandom.com/wiki/Berserk"
    },
    "Bombard Cannon": {
        "image_name": "Bombard cannon aoe2DE.png",
        "strong_vs": [
            "Building",
            "Unit in dense formations",
            "Siege weapon"
        ],
        "weak_vs": [
            "Unit at close range (especially condottieri)",
            "Cavalry",
            "Mangudai"
        ],
        "wiki_link": "https://ageofempires.fandom.com/wiki/Bombard_Cannon"
    },
    "Boyar": {
        "image_name": "BoyarIcon-DE.png",
        "strong_vs": [
            "Skirmisher",
            "Melee unit",
            "Siege weapon"
        ],
        "weak_vs": [
            "Pikeman",
            "Camel rider",
            "Monk"
        ],
        "wiki_link": "https://ageofempires.fandom.com/wiki/Boyar_(Age_of_Empires_II)"
    },
    "Camel Archer": {
        "image_name": "CamelArcherIcon-DE.png",
        "strong_vs": [
            "Slow non-ranged unit",
            "Cavalry archer",
            "Conquistador"
        ],
        "weak_vs": [
            "Huskarl",
            "Skirmisher",
            "Eagle warrior"
        ],
        "wiki_link": "https://ageofempires.fandom.com/wiki/Camel_Archer_(Age_of_Empires_II)"
    },
    "Camel Rider": {
        "image_name": "Camelrider aoe2DE.png",
        "strong_vs": [
            "Skirmisher",
            "Siege weapon",
            "Mounted archer",
            "Cavalry"
        ],
        "weak_vs": [
            "Infantry",
            "Foot archer",
            "Cataphract",
            "Defensive structure"
        ],
        "wiki_link": "https://ageofempires.fandom.com/wiki/Camel_Rider_(Age_of_Empires_II)"
    },
    "Camel Scout": {
        "image_name": "Aoe2de camel scout.png",
        "strong_vs": [
            "Scout cavalry",
            "Skirmisher"
        ],
        "weak_vs": [
            "Spearman",
            "Defensive structure"
        ],
        "wiki_link": "https://ageofempires.fandom.com/wiki/Camel_Scout"
    },
    "Cannon Galleon": {
        "image_name": "Cannon galleon aoe2DE.png",
        "strong_vs": [
            "Building"
        ],
        "weak_vs": [
            "Ship"
        ],
        "wiki_link": "https://ageofempires.fandom.com/wiki/Cannon_Galleon"
    },
    "Capped Ram": {
        "image_name": "Capped ram aoe2DE.png",
        "strong_vs": [
            "Building",
            "Trebuchet",
            "Archer"
        ],
        "weak_vs": [
            "Mangudai",
            "Onager",
            "Melee units especially magyar huszar"
        ],
        "wiki_link": "https://ageofempires.fandom.com/wiki/Capped_Ram"
    },
    "Caravel": {
        "image_name": "CaravelIcon-DE.png",
        "strong_vs": [
            "Buildings melee unit in the shoreline",
            "Cannon galleon",
            "Unit in dense formation",
            "Longboat"
        ],
        "weak_vs": [
            "Fire ship",
            "Turtle ship",
            "Tower",
            "Castle"
        ],
        "wiki_link": "https://ageofempires.fandom.com/wiki/Caravel_(Age_of_Empires_II)"
    },
    "Cataphract": {
        "image_name": "CataphractIcon-DE.png",
        "strong_vs": [
            "Skirmisher",
            "Infantry",
            "Siege weapon",
            "Light cavalry",
            "Camel rider"
        ],
        "weak_vs": [
            "Battle elephant",
            "Knight",
            "Archer",
            "Massed halberdier",
            "Monk"
        ],
        "wiki_link": "https://ageofempires.fandom.com/wiki/Cataphract_(Age_of_Empires_II)"
    },
    "Cavalier": {
        "image_name": "Cavalier aoe2DE.png",
        "strong_vs": [
            "Infantry",
            "Villager",
            "Siege weapon",
            "Light cavalry"
        ],
        "weak_vs": [
            "Boyar",
            "Halberdier",
            "Kamayuk",
            "Berserk"
        ],
        "wiki_link": "https://ageofempires.fandom.com/wiki/Cavalier"
    },
    "Cavalry Archer": {
        "image_name": "Cavalryarcher aoe2DE.png",
        "strong_vs": [
            "Most infantry",
            "Most foot archer with all armor upgrades"
        ],
        "weak_vs": [
            "Genoese crossbowman",
            "Huskarl"
        ],
        "wiki_link": "https://ageofempires.fandom.com/wiki/Cavalry_Archer_(Age_of_Empires_II)"
    },
    "Centurion": {
        "image_name": "Aoe2de roman unique centurion icon.png",
        "strong_vs": [
            "Infantry",
            "Foot archer",
            "Siege weapon",
            "Light cavalry"
        ],
        "weak_vs": [
            "War elephant",
            "Battle elephant",
            "Camel rider",
            "Pikeman"
        ],
        "wiki_link": "https://ageofempires.fandom.com/wiki/Centurion_(Age_of_Empires_II)"
    },
    "Chakram Thrower": {
        "image_name": "Aoe2de Chakram.png",
        "strong_vs": [
            "Slow non ranged unit",
            "Skirmisher",
            "Monk"
        ],
        "weak_vs": [
            "Archer",
            "Ranged siege weapon",
            "Heavy infantry"
        ],
        "wiki_link": "https://ageofempires.fandom.com/wiki/Chakram_Thrower_(Age_of_Empires_II)"
    },
    "Champion": {
        "image_name": "Champion aoe2DE.png",
        "strong_vs": [
            "Skirmisher",
            "Genitour",
            "Halberdier",
            "Camel rider",
            "Eagle warrior",
            "Building",
            "Light cavalry",
            "Huskarl"
        ],
        "weak_vs": [
            "Archer unit",
            "Scorpion",
            "Mangonel",
            "Cataphract",
            "Jaguar warrior",
            "Paladin",
            "Boyar",
            "War elephant"
        ],
        "wiki_link": "https://ageofempires.fandom.com/wiki/Champion"
    },
    "Chu Ko Nu": {
        "image_name": "ChukoNuIcon-DE.png",
        "strong_vs": [
            "Infantry",
            "Archer",
            "Cavalry"
        ],
        "weak_vs": [
            "Skirmisher",
            "Scorpion",
            "Mangonel"
        ],
        "wiki_link": "https://ageofempires.fandom.com/wiki/Chu_Ko_Nu_(Age_of_Empires_II)"
    },
    "Condottiero": {
        "image_name": "CondottieroIcon-DE.png",
        "strong_vs": [
            "Skirmisher",
            "Gunpowder unit",
            "Siege weapon"
        ],
        "weak_vs": [
            "Archers scorpion at long distance",
            "Heavy cavalry",
            "Heavy infantry"
        ],
        "wiki_link": "https://ageofempires.fandom.com/wiki/Condottiero"
    },
    "Conquistador": {
        "image_name": "ConquistadorIcon-DE.png",
        "strong_vs": [
            "Infantry"
        ],
        "weak_vs": [
            "Knight"
        ],
        "wiki_link": "https://ageofempires.fandom.com/wiki/Conquistador_(Age_of_Empires_II)"
    },
    "Coustillier": {
        "image_name": "Aoe2-icon-coustillier.png",
        "strong_vs": [
            "Infantry",
            "Archer",
            "Villager",
            "Siege weapon",
            "Cavalry archer",
            "Light cavalry"
        ],
        "weak_vs": [
            "Kamayuk",
            "Genoese crossbowman",
            "Mameluke",
            "Camel rider",
            "Samurai",
            "War elephant"
        ],
        "wiki_link": "https://ageofempires.fandom.com/wiki/Coustillier"
    },
    "Crossbowman": {
        "image_name": "Crossbowman aoe2DE.png",
        "strong_vs": [
            "Infantry",
            "Villager",
            "Camel unit"
        ],
        "weak_vs": [
            "Skirmisher",
            "Siege unit",
            "Huskarl"
        ],
        "wiki_link": "https://ageofempires.fandom.com/wiki/Crossbowman_(Age_of_Empires_II)"
    },
    "Demolition Raft": {
        "image_name": "Demoraft aoe2DE.png",
        "strong_vs": [
            "Transport ship",
            "Fishing ship"
        ],
        "weak_vs": [
            "Tower",
            "Ranged unit on the shoreline"
        ],
        "wiki_link": "https://ageofempires.fandom.com/wiki/Demolition_Raft"
    },
    "Demolition Ship": {
        "image_name": "Demoship aoe2DE.png",
        "strong_vs": [
            "Transport ship",
            "Fishing ship",
            "Fire ship",
            "Building in the shoreline"
        ],
        "weak_vs": [
            "Turtle ship",
            "Tower",
            "Castle",
            "Ranged unit on the shoreline"
        ],
        "wiki_link": "https://ageofempires.fandom.com/wiki/Demolition_Ship"
    },
    "Dromon": {
        "image_name": "AoE2 Dromon.png",
        "strong_vs": [
            "Building",
            "Siege weapon",
            "Archer"
        ],
        "weak_vs": [
            "Ship",
            "Bombard cannon",
            "Monk"
        ],
        "wiki_link": "https://ageofempires.fandom.com/wiki/Dromon"
    },
    "Eagle Scout": {
        "image_name": "Eaglescout aoe2DE.png",
        "strong_vs": [
            "Scout cavalry",
            "Foot archer"
        ],
        "weak_vs": [
            "Heavy infantry",
            "Heavy cavalry"
        ],
        "wiki_link": "https://ageofempires.fandom.com/wiki/Eagle_Scout_(Age_of_Empires_II)"
    },
    "Eagle Warrior": {
        "image_name": "Eaglewarrior aoe2DE.png",
        "strong_vs": [
            "Foot archer",
            "Siege weapon",
            "Monk",
            "Genitour"
        ],
        "weak_vs": [
            "Gunpowder unit",
            "Slinger",
            "Heavy infantry",
            "Heavy cavalry"
        ],
        "wiki_link": "https://ageofempires.fandom.com/wiki/Eagle_Warrior"
    },
    "Elephant Archer": {
        "image_name": "Aoe2de DOI elephant archer icon.png",
        "strong_vs": [
            "Slow non-ranged unit",
            "Archer"
        ],
        "weak_vs": [
            "Spearman",
            "Kamayuk"
        ],
        "wiki_link": "https://ageofempires.fandom.com/wiki/Elephant_Archer_(Age_of_Empires_II)"
    },
    "Elite Battle Elephant": {
        "image_name": "Elite battle elephant aoe2DE.png",
        "strong_vs": [
            "Most melee unit",
            "Building",
            "Resistant to most foot archers"
        ],
        "weak_vs": [
            "Halberdier",
            "Kamayuk",
            "Genoese crossbowman"
        ],
        "wiki_link": "https://ageofempires.fandom.com/wiki/Elite_Battle_Elephant"
    },
    "Elite Cannon Galleon": {
        "image_name": "Elite cannon galleon aoe2de.png",
        "strong_vs": [
            "Building"
        ],
        "weak_vs": [
            "Ship"
        ],
        "wiki_link": "https://ageofempires.fandom.com/wiki/Elite_Cannon_Galleon"
    },
    "Elite Eagle Warrior": {
        "image_name": "EliteEaglewarrior aoe2DE.png",
        "strong_vs": [
            "Foot archer",
            "Siege weapon",
            "Monk",
            "Halberdier"
        ],
        "weak_vs": [
            "Heavy cavalry",
            "Heavy infantry",
            "Gunpowder unit",
            "Slinger"
        ],
        "wiki_link": "https://ageofempires.fandom.com/wiki/Elite_Eagle_Warrior"
    },
    "Elite Elephant Archer": {
        "image_name": "ElephantArcherIcon-DE.png",
        "strong_vs": [
            "Slow non-ranged unit",
            "Archer"
        ],
        "weak_vs": [
            "Spearman",
            "Kamayuk"
        ],
        "wiki_link": "https://ageofempires.fandom.com/wiki/Elite_Elephant_Archer"
    },
    "Elite Skirmisher": {
        "image_name": "Elite skirmisher aoe2DE.png",
        "strong_vs": [
            "Archer",
            "Spearman line"
        ],
        "weak_vs": [
            "Melee unit",
            "Siege unit"
        ],
        "wiki_link": "https://ageofempires.fandom.com/wiki/Elite_Skirmisher"
    },
    "Elite Steppe Lancer": {
        "image_name": "Elitesteppelancericon.png",
        "strong_vs": [
            "Light cavalry",
            "Skirmisher",
            "Villager",
            "Siege weapon"
        ],
        "weak_vs": [
            "Stronger cavalry",
            "Halberdier",
            "Monk",
            "Camel unit"
        ],
        "wiki_link": "https://ageofempires.fandom.com/wiki/Elite_Steppe_Lancer"
    },
    "Fast Fire Ship": {
        "image_name": "Fastfireship aoe2DE.png",
        "strong_vs": [
            "Transport ship",
            "Fishing ship",
            "Building in the shoreline",
            "Melee unit in the shallows",
            "Galleon",
            "Cannon galleon"
        ],
        "weak_vs": [
            "Demolition ship",
            "Turtle ship",
            "Longboat",
            "Tower",
            "Castle",
            "Ranged siege unit on the shoreline"
        ],
        "wiki_link": "https://ageofempires.fandom.com/wiki/Fast_Fire_Ship"
    },
    "Fire Galley": {
        "image_name": "Fire galley aoe2DE.png",
        "strong_vs": [
            "Transport ship",
            "Building in the shoreline",
            "Melee unit in the shallows"
        ],
        "weak_vs": [
            "Demolition raft",
            "Tower",
            "Ranged siege unit on the shoreline"
        ],
        "wiki_link": "https://ageofempires.fandom.com/wiki/Fire_Galley_(Age_of_Empires_II)"
    },
    "Fire Ship": {
        "image_name": "Fireship aoe2DE.png",
        "strong_vs": [
            "Transport ship",
            "Fishing ship",
            "Building in the shoreline",
            "Melee unit in the shallows",
            "War galley",
            "Cannon galleon"
        ],
        "weak_vs": [
            "Demolition ship",
            "Turtle ship",
            "Longboat",
            "Tower",
            "Castle",
            "Ranged siege unit on the shoreline"
        ],
        "wiki_link": "https://ageofempires.fandom.com/wiki/Fire_Ship_(Age_of_Empires_II)"
    },
    "Fishing Ship": {
        "image_name": "FishingShipDE.png",
        "strong_vs": [
            "Nothing"
        ],
        "weak_vs": [
            "Everything"
        ],
        "wiki_link": "https://ageofempires.fandom.com/wiki/Fishing_Ship_(Age_of_Empires_II)"
    },
    "Flaming Camel": {
        "image_name": "Flaming camel icon.png",
        "strong_vs": [
            "Mounted units especially elephant"
        ],
        "weak_vs": [
            "Foot archer"
        ],
        "wiki_link": "https://ageofempires.fandom.com/wiki/Flaming_Camel"
    },
    "Flemish Militia": {
        "image_name": "Aoe2-icon-flemish-militia.png",
        "strong_vs": [
            "Skirmisher",
            "Cavalry",
            "Spearman",
            "Ram",
            "Camel rider",
            "Eagle warrior"
        ],
        "weak_vs": [
            "Archer unit",
            "Scorpion",
            "Mangonel",
            "Cataphract",
            "Teutonic knight",
            "Samurai"
        ],
        "wiki_link": "https://ageofempires.fandom.com/wiki/Flemish_Militia"
    },
    "Galleon": {
        "image_name": "Galleon aoe2DE.png",
        "strong_vs": [
            "Transport ship",
            "Fishing ship",
            "Building in the shoreline",
            "Melee unit in the shoreline",
            "Demolition ship",
            "Cannon galleon"
        ],
        "weak_vs": [
            "Fire ship",
            "Turtle ship",
            "Longboat",
            "Tower",
            "Castle",
            "Ranged siege unit on the shoreline"
        ],
        "wiki_link": "https://ageofempires.fandom.com/wiki/Galleon_(Age_of_Empires_II)"
    },
    "Galley": {
        "image_name": "Galley aoe2DE.png",
        "strong_vs": [
            "Transport ship",
            "Fishing ship",
            "Building in the shoreline",
            "Melee unit in the shoreline"
        ],
        "weak_vs": [
            "Fire galley",
            "Tower",
            "Castle",
            "Ranged unit on the shoreline"
        ],
        "wiki_link": "https://ageofempires.fandom.com/wiki/Galley_(Age_of_Empires_II)"
    },
    "Gbeto": {
        "image_name": "GbetoIcon-DE.png",
        "strong_vs": [
            "Skirmisher",
            "Pikeman",
            "Cavalry archer",
            "Battering ram",
            "Infantry"
        ],
        "weak_vs": [
            "Archer",
            "Scorpion",
            "Mangonel",
            "Boyar",
            "Teutonic knight"
        ],
        "wiki_link": "https://ageofempires.fandom.com/wiki/Gbeto"
    },
    "Genitour": {
        "image_name": "GenitourIcon-DE.png",
        "strong_vs": [
            "Archer",
            "Monk",
            "Most infantry"
        ],
        "weak_vs": [
            "Camel rider",
            "Siege unit",
            "Huskarl"
        ],
        "wiki_link": "https://ageofempires.fandom.com/wiki/Genitour"
    },
    "Genoese Crossbowman": {
        "image_name": "GenoeseCrossbowmanIcon-DE.png",
        "strong_vs": [
            "Cavalry",
            "Mounted archer",
            "Infantry"
        ],
        "weak_vs": [
            "Skirmisher",
            "Siege weapon",
            "Huskarl"
        ],
        "wiki_link": "https://ageofempires.fandom.com/wiki/Genoese_Crossbowman"
    },
    "Ghulam": {
        "image_name": "Aoe2de Ghulam.png",
        "strong_vs": [
            "Foot archer",
            "Villager",
            "Siege unit",
            "Eagle warrior"
        ],
        "weak_vs": [
            "Champion",
            "Jaguar warrior",
            "Samurai",
            "Teutonic knight"
        ],
        "wiki_link": "https://ageofempires.fandom.com/wiki/Ghulam_(Age_of_Empires_II)"
    },
    "Halberdier": {
        "image_name": "Halberdier aoe2DE.png",
        "strong_vs": [
            "Cavalry"
        ],
        "weak_vs": [
            "Archer"
        ],
        "wiki_link": "https://ageofempires.fandom.com/wiki/Halberdier_(Age_of_Empires_II)"
    },
    "Hand Cannoneer": {
        "image_name": "Hand cannoneer aoe2DE.png",
        "strong_vs": [
            "Infantry",
            "Camel rider"
        ],
        "weak_vs": [
            "Skirmisher",
            "Scorpion"
        ],
        "wiki_link": "https://ageofempires.fandom.com/wiki/Hand_Cannoneer"
    },
    "Heavy Camel Rider": {
        "image_name": "Aoe2 heavycamelriderDE.png",
        "strong_vs": [
            "Skirmisher",
            "Siege weapon",
            "Mounted archer",
            "Cavalry"
        ],
        "weak_vs": [
            "Infantry",
            "Foot archer",
            "Cataphract",
            "Defensive structure"
        ],
        "wiki_link": "https://ageofempires.fandom.com/wiki/Heavy_Camel_Rider"
    },
    "Heavy Cavalry Archer": {
        "image_name": "Heavycavalryarcher aoe2de.png",
        "strong_vs": [
            "Slow non-ranged unit",
            "Foot archers (with both parthian tactics ring archer armor)"
        ],
        "weak_vs": [
            "Camel rider",
            "Skirmisher"
        ],
        "wiki_link": "https://ageofempires.fandom.com/wiki/Heavy_Cavalry_Archer"
    },
    "Heavy Demolition Ship": {
        "image_name": "Heavydemoship aoe2de.png",
        "strong_vs": [
            "Transport ship",
            "Fishing ship",
            "Building in the shoreline",
            "Melee unit in the shallows"
        ],
        "weak_vs": [
            "Turtle ship",
            "Tower",
            "Castle",
            "Ranged unit on the shoreline"
        ],
        "wiki_link": "https://ageofempires.fandom.com/wiki/Heavy_Demolition_Ship"
    },
    "Heavy Scorpion": {
        "image_name": "Heavyscorpion aoe2DE.png",
        "strong_vs": [
            "Massed infantry archer",
            "Elephant",
            "Slow-moving unit"
        ],
        "weak_vs": [
            "Cavalry",
            "Fast-moving melee unit",
            "Magyar huszar"
        ],
        "wiki_link": "https://ageofempires.fandom.com/wiki/Heavy_Scorpion"
    },
    "Houfnice": {
        "image_name": "Aoe2-icon--houfnice.png",
        "strong_vs": [
            "Building",
            "Unit in dense formations",
            "Slow moving unit",
            "Ship",
            "Foot archer"
        ],
        "weak_vs": [
            "Melee unit at close range",
            "Especially condottieri",
            "Eagle warrior",
            "Magyar huszar",
            "Mangudai"
        ],
        "wiki_link": "https://ageofempires.fandom.com/wiki/Houfnice"
    },
    "Huskarl": {
        "image_name": "HuskarlIcon-DE.png",
        "strong_vs": [
            "Archer",
            "Building",
            "Eagle warrior",
            "Camel rider",
            "Scorpion"
        ],
        "weak_vs": [
            "Mangonel",
            "Heavy infantry",
            "Cavalry",
            "Mameluke",
            "Ranged infantry"
        ],
        "wiki_link": "https://ageofempires.fandom.com/wiki/Huskarl_(Age_of_Empires_II)"
    },
    "Hussar": {
        "image_name": "Hussar aoe2DE.png",
        "strong_vs": [
            "Archer",
            "Siege weapon",
            "Monk"
        ],
        "weak_vs": [
            "Infantry",
            "Cavalry",
            "Genoese crossbowman"
        ],
        "wiki_link": "https://ageofempires.fandom.com/wiki/Hussar_(Age_of_Empires_II)"
    },
    "Hussite Wagon": {
        "image_name": "Aoe2-icon-hussite-wagon.png",
        "strong_vs": [
            "Pikeman",
            "Archer unit"
        ],
        "weak_vs": [
            "Mangonel-line bombard cannon-line",
            "Cavalry"
        ],
        "wiki_link": "https://ageofempires.fandom.com/wiki/Hussite_Wagon"
    },
    "Imperial Camel Rider": {
        "image_name": "ImperialCamelRiderIcon-DE.png",
        "strong_vs": [
            "Skirmisher",
            "Siege weapon",
            "Mounted archer",
            "Cavalry"
        ],
        "weak_vs": [
            "Foot archer",
            "Halberdier",
            "Kamayuk",
            "Teutonic knight"
        ],
        "wiki_link": "https://ageofempires.fandom.com/wiki/Imperial_Camel_Rider"
    },
    "Imperial Skirmisher": {
        "image_name": "Imperialskirmishericon-DE.png",
        "strong_vs": [
            "Archer",
            "Spearman line"
        ],
        "weak_vs": [
            "Melee unit",
            "Siege unit"
        ],
        "wiki_link": "https://ageofempires.fandom.com/wiki/Imperial_Skirmisher"
    },
    "Jaguar Warrior": {
        "image_name": "JaguarWarriorIcon-DE.png",
        "strong_vs": [
            "Skirmisher",
            "Infantry",
            "Building"
        ],
        "weak_vs": [
            "Scorpion",
            "Mangonel",
            "Heavy cavalry"
        ],
        "wiki_link": "https://ageofempires.fandom.com/wiki/Jaguar_Warrior"
    },
    "Janissary": {
        "image_name": "JanissaryIcon-DE.png",
        "strong_vs": [
            "Infantry",
            "Building"
        ],
        "weak_vs": [
            "Skirmisher",
            "Scorpion"
        ],
        "wiki_link": "https://ageofempires.fandom.com/wiki/Janissary_(Age_of_Empires_II)"
    },
    "Kamayuk": {
        "image_name": "KamayukIcon-DE.png",
        "strong_vs": [
            "Skirmisher",
            "Cavalry",
            "Spearman",
            "Eagle warrior"
        ],
        "weak_vs": [
            "Scorpion",
            "Mangonel",
            "Mounted archer",
            "Hcannoneer"
        ],
        "wiki_link": "https://ageofempires.fandom.com/wiki/Kamayuk"
    },
    "Karambit Warrior": {
        "image_name": "Karambitwarrioricon-DE.png",
        "strong_vs": [
            "Skirmisher",
            "Halberdier",
            "Eagle warrior",
            "Ram",
            "Ghulam",
            "Light cavalry"
        ],
        "weak_vs": [
            "Archer",
            "Gunpowder unit",
            "Scorpion",
            "Mangonel",
            "Heavy cavalry elephant",
            "Heavy infantry"
        ],
        "wiki_link": "https://ageofempires.fandom.com/wiki/Karambit_Warrior"
    },
    "Keshik": {
        "image_name": "Keshikicon.png",
        "strong_vs": [
            "Infantry",
            "Archer",
            "Villager",
            "Siege weapon",
            "Light cavalry"
        ],
        "weak_vs": [
            "Boyar",
            "Pikeman",
            "Kamayuk",
            "Berserk",
            "Genoese crossbowman"
        ],
        "wiki_link": "https://ageofempires.fandom.com/wiki/Keshik_(Age_of_Empires_II)"
    },
    "Kipchak": {
        "image_name": "Kipchakicon.png",
        "strong_vs": [
            "Slow non-ranged unit",
            "Ram",
            "Monk"
        ],
        "weak_vs": [
            "Genoese crossbowman",
            "Skirmisher",
            "Genitour"
        ],
        "wiki_link": "https://ageofempires.fandom.com/wiki/Kipchak"
    },
    "Knight": {
        "image_name": "Knight aoe2DE.png",
        "strong_vs": [
            "Infantry",
            "Villager",
            "Siege weapon",
            "Light cavalry"
        ],
        "weak_vs": [
            "Boyar",
            "Pikeman",
            "Kamayuk",
            "Berserk"
        ],
        "wiki_link": "https://ageofempires.fandom.com/wiki/Knight_(Age_of_Empires_II)"
    },
    "Konnik": {
        "image_name": "Konnikicon.png",
        "strong_vs": [
            "Infantry",
            "Siege weapons (mounted)",
            "Light cavalry"
        ],
        "weak_vs": [
            "Archers (dismounted)",
            "Pikemen (mounted)",
            "Monk"
        ],
        "wiki_link": "https://ageofempires.fandom.com/wiki/Konnik"
    },
    "Legionary": {
        "image_name": "AoE2 DE Legionary new icon.png",
        "strong_vs": [
            "Skirmisher",
            "Genitour",
            "Halberdier",
            "Camel rider",
            "Eagle warrior",
            "Building",
            "Light cavalry",
            "Huskarl"
        ],
        "weak_vs": [
            "Archer unit",
            "Scorpion",
            "Mangonel",
            "Cataphract",
            "Jaguar warrior",
            "Paladin",
            "Boyar",
            "War elephant"
        ],
        "wiki_link": "https://ageofempires.fandom.com/wiki/Legionary_(Age_of_Empires_II)"
    },
    "Leitis": {
        "image_name": "Leitisicon.png",
        "strong_vs": [
            "Melee units (especially serjeant",
            "Teutonic knight",
            "Boyars)"
        ],
        "weak_vs": [
            "Pikeman",
            "Kamayuk",
            "Genoese crossbowman"
        ],
        "wiki_link": "https://ageofempires.fandom.com/wiki/Leitis"
    },
    "Light Cavalry": {
        "image_name": "Lightcavalry aoe2DE.png",
        "strong_vs": [
            "Skirmisher",
            "Villager"
        ],
        "weak_vs": [
            "Most melee unit",
            "Genoese crossbowman"
        ],
        "wiki_link": "https://ageofempires.fandom.com/wiki/Light_Cavalry_(Age_of_Empires_II)"
    },
    "Long Swordsman": {
        "image_name": "Longswordsman aoe2DE.png",
        "strong_vs": [
            "Skirmisher",
            "Camel rider",
            "Eagle warrior",
            "Building",
            "Light cavalry",
            "Pikeman"
        ],
        "weak_vs": [
            "Archer",
            "Scorpion",
            "Cataphract",
            "Jaguar warrior",
            "Boyar",
            "Teutonic knight"
        ],
        "wiki_link": "https://ageofempires.fandom.com/wiki/Long_Swordsman_(Age_of_Empires_II)"
    },
    "Longboat": {
        "image_name": "LongboatIcon-DE.png",
        "strong_vs": [
            "Transport ship",
            "Fishing ship",
            "Building",
            "Lunit in the shoreline shallows",
            "Turtle ships (hit-and-run only)",
            "Cannon galleon",
            "Thirisadai (equal resources only)"
        ],
        "weak_vs": [
            "Fire ships (only in small groups)",
            "Demolition ship",
            "Samurai (in the shallows)",
            "Tower",
            "Castle",
            "Ranged siege unit on the shoreline",
            "Caravels (in large fleet battles)"
        ],
        "wiki_link": "https://ageofempires.fandom.com/wiki/Longboat_(Age_of_Empires_II)"
    },
    "Longbowman": {
        "image_name": "LongbowmanIcon-DE.png",
        "strong_vs": [
            "Infantry",
            "Archer"
        ],
        "weak_vs": [
            "Skirmisher",
            "Siege weapon"
        ],
        "wiki_link": "https://ageofempires.fandom.com/wiki/Longbowman_(Age_of_Empires_II)"
    },
    "Magyar Huszar": {
        "image_name": "MagyarHuszarIcon-DE.png",
        "strong_vs": [
            "Siege weapon",
            "Archer",
            "Other light cavalry"
        ],
        "weak_vs": [
            "Boyar",
            "Pikeman",
            "Kamayuk"
        ],
        "wiki_link": "https://ageofempires.fandom.com/wiki/Magyar_Huszar"
    },
    "Mameluke": {
        "image_name": "MamelukeIcon-DE.png",
        "strong_vs": [
            "Siege weapon",
            "Skirmisher",
            "Mounted archer except camel archers",
            "Melee units especially cavalry"
        ],
        "weak_vs": [
            "Foot archer",
            "Camel rider",
            "Monk",
            "Teutonic knight"
        ],
        "wiki_link": "https://ageofempires.fandom.com/wiki/Mameluke_(Age_of_Empires_II)"
    },
    "Man-at-Arms": {
        "image_name": "Manatarms aoe2DE.png",
        "strong_vs": [
            "Skirmisher",
            "Scout cavalry"
        ],
        "weak_vs": [
            "Archer",
            "Scorpion"
        ],
        "wiki_link": "https://ageofempires.fandom.com/wiki/Man-at-Arms_(Age_of_Empires_II)"
    },
    "Mangonel": {
        "image_name": "Mangonel aoe2DE.png",
        "strong_vs": [
            "Building",
            "Archer",
            "Siege weapon"
        ],
        "weak_vs": [
            "Fast moving melee units especially magyar huszars eagle warrior",
            "Mangudai",
            "Monk with sancity redemption"
        ],
        "wiki_link": "https://ageofempires.fandom.com/wiki/Mangonel_(Age_of_Empires_II)"
    },
    "Mangudai": {
        "image_name": "MangudaiIcon-DE.png",
        "strong_vs": [
            "Infantry",
            "Siege weapon"
        ],
        "weak_vs": [
            "Paladin",
            "Camel rider"
        ],
        "wiki_link": "https://ageofempires.fandom.com/wiki/Mangudai_(Age_of_Empires_II)"
    },
    "Militia": {
        "image_name": "MilitiaDE.png",
        "strong_vs": [
            "Skirmisher",
            "Scout cavalry"
        ],
        "weak_vs": [
            "Archer",
            "Wall"
        ],
        "wiki_link": "https://ageofempires.fandom.com/wiki/Militia_(Age_of_Empires_II)"
    },
    "Missionary": {
        "image_name": "MissionaryIcon-DE.png",
        "strong_vs": [
            "Slow non-ranged unit",
            "Buildings without conversion defense",
            "Knight"
        ],
        "weak_vs": [
            "Archer",
            "Eagle warrior",
            "Light cavalry"
        ],
        "wiki_link": "https://ageofempires.fandom.com/wiki/Missionary_(Age_of_Empires_II)"
    },
    "Monk": {
        "image_name": "Monk aoe2DE.png",
        "strong_vs": [
            "Slow and/or expensive non-ranged units (such as battle elephants or knights)",
            "Onagers (with redemption sanctity/block printing)"
        ],
        "weak_vs": [
            "Eagle warrior",
            "Light cavalry"
        ],
        "wiki_link": "https://ageofempires.fandom.com/wiki/Monk_(Age_of_Empires_II)"
    },
    "Obuch": {
        "image_name": "Aoe2-icon--obuch.png",
        "strong_vs": [
            "Skirmisher",
            "Camel rider",
            "Building",
            "Light cavalry",
            "Most infantry",
            "Heavily-armored unit"
        ],
        "weak_vs": [
            "Samurai",
            "Gunpowder mounted archer",
            "Scorpion",
            "Berserk",
            "Cataphract",
            "Jaguar warrior"
        ],
        "wiki_link": "https://ageofempires.fandom.com/wiki/Obuch"
    },
    "Onager": {
        "image_name": "Onager aoe2DE.png",
        "strong_vs": [
            "Building",
            "Archer",
            "Siege weapon except bombard cannons",
            "Unit in dense formations"
        ],
        "weak_vs": [
            "Fast moving melee units especially magyar huszars eagle warrior",
            "Mangudai",
            "Bombard cannon",
            "Monk with block printing redemption"
        ],
        "wiki_link": "https://ageofempires.fandom.com/wiki/Onager_(Age_of_Empires_II)"
    },
    "Organ Gun": {
        "image_name": "OrganGunIcon-DE.png",
        "strong_vs": [
            "Villager",
            "Infantry",
            "Mob of units"
        ],
        "weak_vs": [
            "Condottieri",
            "Cavalry",
            "Onager"
        ],
        "wiki_link": "https://ageofempires.fandom.com/wiki/Organ_Gun_(Age_of_Empires_II)"
    },
    "Paladin": {
        "image_name": "Paladin aoe2DE.png",
        "strong_vs": [
            "Infantry",
            "Foot archer",
            "Siege weapon",
            "Light cavalry"
        ],
        "weak_vs": [
            "Halberdier",
            "Heavy camel rider",
            "Monk",
            "Elite battle elephant"
        ],
        "wiki_link": "https://ageofempires.fandom.com/wiki/Paladin"
    },
    "Petard": {
        "image_name": "Petard aoe2DE.png",
        "strong_vs": [
            "Building"
        ],
        "weak_vs": [
            "Ranged unit"
        ],
        "wiki_link": "https://ageofempires.fandom.com/wiki/Petard_(Age_of_Empires_II)"
    },
    "Pikeman": {
        "image_name": "Aoe2-infantry-2-pikeman.png",
        "strong_vs": [
            "Cavalry"
        ],
        "weak_vs": [
            "Archer"
        ],
        "wiki_link": "https://ageofempires.fandom.com/wiki/Pikeman_(Age_of_Empires_II)"
    },
    "Plumed Archer": {
        "image_name": "PlumedArcherIcon-DE.png",
        "strong_vs": [
            "Infantry",
            "Archer",
            "Villager",
            "Hcannoneer",
            "Camel rider",
            "Mameluke"
        ],
        "weak_vs": [
            "Skirmisher",
            "Siege weapon",
            "Huskarl",
            "Rattan archer",
            "Genitour",
            "War wagon"
        ],
        "wiki_link": "https://ageofempires.fandom.com/wiki/Plumed_Archer"
    },
    "Ratha": {
        "image_name": "Aoe2de ratha ranged.png",
        "strong_vs": [
            "Archer",
            "Siege weapons (melee)",
            "Slow non ranged units (ranged)",
            "Villager"
        ],
        "weak_vs": [
            "Skirmisher",
            "Rattan archer",
            "Huskarl",
            "Samurai"
        ],
        "wiki_link": "https://ageofempires.fandom.com/wiki/Ratha"
    },
    "Rattan Archer": {
        "image_name": "Rattanarchericon-DE.png",
        "strong_vs": [
            "Archer",
            "Cavalry archer",
            "Infantry",
            "Villager"
        ],
        "weak_vs": [
            "Cavalry",
            "Skirmisher",
            "Genitour",
            "Huskarl"
        ],
        "wiki_link": "https://ageofempires.fandom.com/wiki/Rattan_Archer"
    },
    "Samurai": {
        "image_name": "SamuraiIcon-DE.png",
        "strong_vs": [
            "Building",
            "Eagle warrior",
            "Pikeman",
            "Skirmisher",
            "Light cavalry",
            "Melee unique unit"
        ],
        "weak_vs": [
            "Archer",
            "Scorpion",
            "Hcannoneer",
            "Paladin",
            "Battle elephant",
            "Legionary"
        ],
        "wiki_link": "https://ageofempires.fandom.com/wiki/Samurai_(Age_of_Empires_II)"
    },
    "Scorpion": {
        "image_name": "Scorpion aoe2DE.png",
        "strong_vs": [
            "Massed infantry archer",
            "Elephant",
            "Slow-moving unit"
        ],
        "weak_vs": [
            "Cavalry",
            "Fast-moving melee unit",
            "Magyar huszar"
        ],
        "wiki_link": "https://ageofempires.fandom.com/wiki/Scorpion"
    },
    "Scout Cavalry": {
        "image_name": "Scoutcavalry aoe2DE.png",
        "strong_vs": [
            "Skirmisher",
            "Villager"
        ],
        "weak_vs": [
            "Infantry",
            "Cavalry"
        ],
        "wiki_link": "https://ageofempires.fandom.com/wiki/Scout_Cavalry_(Age_of_Empires_II)"
    },
    "Serjeant": {
        "image_name": "Aoe2-icon-serjeant.png",
        "strong_vs": [
            "Archer",
            "Infantry with less melee armor",
            "Skirmisher",
            "Building",
            "Hussar",
            "Camel rider"
        ],
        "weak_vs": [
            "Scorpion",
            "Mangonel",
            "Hcannoneer",
            "Conquistador",
            "Janissary",
            "Slinger"
        ],
        "wiki_link": "https://ageofempires.fandom.com/wiki/Serjeant"
    },
    "Shotel Warrior": {
        "image_name": "Shotelwarrioricon-DE.png",
        "strong_vs": [
            "Building",
            "Villager",
            "Skirmisher",
            "Pikeman",
            "Eagle warrior",
            "Light cavalry"
        ],
        "weak_vs": [
            "Archer",
            "Scorpion",
            "Mangonel",
            "Hcannoneer",
            "Janissary",
            "Heavy infantry"
        ],
        "wiki_link": "https://ageofempires.fandom.com/wiki/Shotel_Warrior_(Age_of_Empires_II)"
    },
    "Shrivamsha Rider": {
        "image_name": "Aoe2de shrivamsha rider.png",
        "strong_vs": [
            "Archer",
            "Siege weapon",
            "Villager",
            "Gbeto",
            "Throwing axeman"
        ],
        "weak_vs": [
            "Pikeman",
            "Kamayuk",
            "Camel rider",
            "Samurai",
            "Most melee unit"
        ],
        "wiki_link": "https://ageofempires.fandom.com/wiki/Shrivamsha_Rider"
    },
    "Siege Elephant": {
        "image_name": "AoE2DE Siege Elephant icon.png",
        "strong_vs": [
            "Building",
            "Archer"
        ],
        "weak_vs": [
            "Infantry",
            "Flaming camel"
        ],
        "wiki_link": "https://ageofempires.fandom.com/wiki/Siege_Elephant_(Age_of_Empires_II)"
    },
    "Siege Onager": {
        "image_name": "Siege onager aoe2DE.png",
        "strong_vs": [
            "Building",
            "Archer",
            "Siege weapon except bombard cannons",
            "Unit in dense formations"
        ],
        "weak_vs": [
            "Fast moving melee units especially magyar huszars eagle warrior",
            "Mangudai",
            "Bombard cannon",
            "Monk with block printing redemption"
        ],
        "wiki_link": "https://ageofempires.fandom.com/wiki/Siege_Onager"
    },
    "Siege Ram": {
        "image_name": "Siege ram aoe2DE.png",
        "strong_vs": [
            "Building",
            "Trebuchet"
        ],
        "weak_vs": [
            "Mangudai",
            "Onager"
        ],
        "wiki_link": "https://ageofempires.fandom.com/wiki/Siege_Ram"
    },
    "Siege Tower": {
        "image_name": "Siegetower aoe2DE.png",
        "strong_vs": [
            "Archer",
            "Wall"
        ],
        "weak_vs": [
            "Melee unit",
            "Especially magyar huszars eagle warrior"
        ],
        "wiki_link": "https://ageofempires.fandom.com/wiki/Siege_Tower_(Age_of_Empires_II)"
    },
    "Skirmisher": {
        "image_name": "Skirmisher aoe2DE.png",
        "strong_vs": [
            "Archer",
            "Spearman"
        ],
        "weak_vs": [
            "Melee unit",
            "Siege unit"
        ],
        "wiki_link": "https://ageofempires.fandom.com/wiki/Skirmisher_(Age_of_Empires_II)"
    },
    "Slinger": {
        "image_name": "SlingerIcon-DE.png",
        "strong_vs": [
            "Infantry",
            "Villager"
        ],
        "weak_vs": [
            "Skirmisher",
            "Cavalry"
        ],
        "wiki_link": "https://ageofempires.fandom.com/wiki/Slinger_(Age_of_Empires_II)"
    },
    "Spearman": {
        "image_name": "Spearman aoe2DE.png",
        "strong_vs": [
            "Cavalry"
        ],
        "weak_vs": [
            "Archer"
        ],
        "wiki_link": "https://ageofempires.fandom.com/wiki/Spearman_(Age_of_Empires_II)"
    },
    "Steppe Lancer": {
        "image_name": "Steppelancericon.png",
        "strong_vs": [
            "Infantry",
            "Light cavalry",
            "Villager",
            "Siege weapon"
        ],
        "weak_vs": [
            "Archer",
            "Stronger cavalry",
            "Pikeman",
            "Camel unit"
        ],
        "wiki_link": "https://ageofempires.fandom.com/wiki/Steppe_Lancer"
    },
    "Tarkan": {
        "image_name": "TarkanIcon-DE.png",
        "strong_vs": [
            "Archer",
            "Siege weapon",
            "Light cavalry",
            "Building"
        ],
        "weak_vs": [
            "Infantry",
            "Heavy cavalry",
            "Genoese crossbowman",
            "Mameluke"
        ],
        "wiki_link": "https://ageofempires.fandom.com/wiki/Tarkan"
    },
    "Teutonic Knight": {
        "image_name": "TeutonicKnightIcon-DE.png",
        "strong_vs": [
            "Skirmisher",
            "Melee unit",
            "Building"
        ],
        "weak_vs": [
            "Archer",
            "Scorpion",
            "Mangonel"
        ],
        "wiki_link": "https://ageofempires.fandom.com/wiki/Teutonic_Knight"
    },
    "Thirisadai": {
        "image_name": "Aoe2de Thirisadai.png",
        "strong_vs": [
            "Galleon",
            "Cannon galleon",
            "Caravel",
            "Units building on the shoreline"
        ],
        "weak_vs": [
            "Castle",
            "Tower",
            "Fire ships (if massed)",
            "Demolition ships (equal resources)"
        ],
        "wiki_link": "https://ageofempires.fandom.com/wiki/Thirisadai"
    },
    "Throwing Axeman": {
        "image_name": "ThrowingAxemanIcon-DE.png",
        "strong_vs": [
            "Skirmisher",
            "Halberdier",
            "Eagle warrior",
            "Ram",
            "Trebuchet",
            "Building",
            "Light cavalry",
            "Huskarl",
            "Camel rider"
        ],
        "weak_vs": [
            "Archer",
            "Scorpion",
            "Mangonel",
            "Jaguar warrior",
            "Boyar",
            "Cataphract",
            "Samurai",
            "Teutonic knight",
            "Paladin"
        ],
        "wiki_link": "https://ageofempires.fandom.com/wiki/Throwing_Axeman_(Age_of_Empires_II)"
    },
    "Trade Cart": {
        "image_name": "Tradecart aoe2DE.png",
        "strong_vs": null,
        "weak_vs": null,
        "wiki_link": "https://ageofempires.fandom.com/wiki/Trade_Cart_(Age_of_Empires_II)"
    },
    "Trade Cog": {
        "image_name": "Trade cog aoe2DE.png",
        "strong_vs": [
            "Nothing"
        ],
        "weak_vs": [
            "Everything"
        ],
        "wiki_link": "https://ageofempires.fandom.com/wiki/Trade_Cog"
    },
    "Transport Ship": {
        "image_name": "Transportship aoe2DE.png",
        "strong_vs": null,
        "weak_vs": null,
        "wiki_link": "https://ageofempires.fandom.com/wiki/Transport_Ship_(Age_of_Empires_II)"
    },
    "Trebuchet": {
        "image_name": "Trebuchet aoe2DE.png",
        "strong_vs": [
            "Building",
            "Archer unit"
        ],
        "weak_vs": [
            "Melee units (especially magyar huszars eagle warriors)",
            "Ram"
        ],
        "wiki_link": "https://ageofempires.fandom.com/wiki/Trebuchet"
    },
    "Turtle Ship": {
        "image_name": "TurtleShipIcon-DE.png",
        "strong_vs": [
            "Ship at close distance",
            "Building on the shoreline",
            "Unit on the shoreline or shallows"
        ],
        "weak_vs": [
            "Bombard cannon",
            "Monk",
            "Castle"
        ],
        "wiki_link": "https://ageofempires.fandom.com/wiki/Turtle_Ship"
    },
    "Two-Handed Swordsman": {
        "image_name": "Twohanded aoe2DE.png",
        "strong_vs": [
            "Skirmisher",
            "Halberdier",
            "Camel rider",
            "Eagle warrior",
            "Building",
            "Light cavalry"
        ],
        "weak_vs": [
            "Archer",
            "Scorpion",
            "Cataphract",
            "Jaguar warrior",
            "Boyar",
            "Teutonic knight"
        ],
        "wiki_link": "https://ageofempires.fandom.com/wiki/Two-Handed_Swordsman"
    },
    "Urumi Swordsman": {
        "image_name": "Aoe2de Urumi.png",
        "strong_vs": [
            "Infantry",
            "Skirmisher",
            "Light cavalry"
        ],
        "weak_vs": [
            "Archer",
            "Scorpion",
            "Cataphract"
        ],
        "wiki_link": "https://ageofempires.fandom.com/wiki/Urumi_Swordsman_(Age_of_Empires_II)"
    },
    "Villager": {
        "image_name": "MaleVillDE.jpg",
        "strong_vs": [
            "Most building"
        ],
        "weak_vs": [
            "Almost everything"
        ],
        "wiki_link": "https://ageofempires.fandom.com/wiki/Villager_(Age_of_Empires_II)"
    },
    "War Elephant": {
        "image_name": "WarElephantIcon-DE.png",
        "strong_vs": [
            "Building",
            "Melee unit"
        ],
        "weak_vs": [
            "Pikeman",
            "Kamayuk"
        ],
        "wiki_link": "https://ageofempires.fandom.com/wiki/War_Elephant_(Age_of_Empires_II)"
    },
    "War Galley": {
        "image_name": "War galley aoe2DE.png",
        "strong_vs": [
            "Building in the shoreline",
            "Melee unit in the shoreline",
            "Demolition ship"
        ],
        "weak_vs": [
            "Fire ship",
            "Turtle ship",
            "Longboat"
        ],
        "wiki_link": "https://ageofempires.fandom.com/wiki/War_Galley_(Age_of_Empires_II)"
    },
    "War Wagon": {
        "image_name": "WarWagonIcon-DE.png",
        "strong_vs": [
            "Infantry",
            "Archer",
            "Building"
        ],
        "weak_vs": [
            "Cavalry",
            "Genoese crossbowman",
            "Huskarl"
        ],
        "wiki_link": "https://ageofempires.fandom.com/wiki/War_Wagon_(Age_of_Empires_II)"
    },
    "Winged Hussar": {
        "image_name": "Aoe2-icon-winged-hussar.png",
        "strong_vs": [
            "Archer",
            "Siege weapon",
            "Monk"
        ],
        "weak_vs": [
            "Most melee unit",
            "Genoese crossbowman",
            "Spearman-line"
        ],
        "wiki_link": "https://ageofempires.fandom.com/wiki/Winged_Hussar_(Age_of_Empires_II)"
    },
    "Woad Raider": {
        "image_name": "WoadRaiderIcon-DE.png",
        "strong_vs": [
            "Skirmisher",
            "Halberdier",
            "Eagle warrior",
            "Building",
            "Light cavalry"
        ],
        "weak_vs": [
            "Archer",
            "Knight",
            "Battle elephant",
            "Jaguar warrior",
            "Cataphract"
        ],
        "wiki_link": "https://ageofempires.fandom.com/wiki/Woad_Raider"
    },
    "Xolotl Warrior": {
        "image_name": "Xolotlicon.png",
        "strong_vs": [
            "Infantry",
            "Villager",
            "Siege weapon",
            "Light cavalry"
        ],
        "weak_vs": [
            "Boyar",
            "Pikeman",
            "Kamayuk",
            "Berserk"
        ],
        "wiki_link": "https://ageofempires.fandom.com/wiki/Xolotl_Warrior"
    }
}